{
    "SelfDriving": {
        "checkpoints": [
            {
                "steps": 242328,
                "file_path": "results\\RayCastTest3\\SelfDriving\\SelfDriving-242328.onnx",
                "reward": -3.8599997758865356,
                "creation_time": 1713708239.3161995,
                "auxillary_file_paths": [
                    "results\\RayCastTest3\\SelfDriving\\SelfDriving-242328.pt"
                ]
            }
        ],
        "final_checkpoint": {
            "steps": 242328,
            "file_path": "results\\RayCastTest3\\SelfDriving.onnx",
            "reward": -3.8599997758865356,
            "creation_time": 1713708239.3161995,
            "auxillary_file_paths": [
                "results\\RayCastTest3\\SelfDriving\\SelfDriving-242328.pt"
            ]
        }
    },
    "metadata": {
        "stats_format_version": "0.3.0",
        "mlagents_version": "0.28.0",
        "torch_version": "1.7.1+cu110"
    }
}